unisim/__init__.py
unisim/config.py
unisim/dataclass.py
unisim/enums.py
unisim/indexer.py
unisim/textsim.py
unisim/types.py
unisim/unisim.py
unisim/backend/__init__.py
unisim/backend/load_backend.py
unisim/backend/onnx.py
unisim/backend/tf.py
unisim/embedder/__init__.py
unisim/embedder/embedder.py
unisim/embedder/models/text/retsim/v1.onnx
unisim/embedder/models/text/retsim/v1/fingerprint.pb
unisim/embedder/models/text/retsim/v1/keras_metadata.pb
unisim/embedder/models/text/retsim/v1/saved_model.pb
unisim/embedder/models/text/retsim/v1/variables/variables.data-00000-of-00001
unisim/embedder/models/text/retsim/v1/variables/variables.index
unisim/embedder/text/__init__.py
unisim/embedder/text/binarizer.py
unisim/embedder/text/text_embedder.py
unisim-1.0.1.dist-info/LICENSE
unisim-1.0.1.dist-info/METADATA
unisim-1.0.1.dist-info/WHEEL
unisim-1.0.1.dist-info/top_level.txt
unisim-1.0.1.dist-info/RECORD
