Metadata-Version: 2.1
Name: unisim
Version: 1.0.1
Summary: UniSim: Universal Similarity
Home-page: https://github.com/google/unisim
Author: Google
Author-email: unisim@google.com
License: MIT
Classifier: Development Status :: 3 - Alpha
Classifier: Environment :: Console
Classifier: License :: OSI Approved :: MIT License
Classifier: Intended Audience :: Science/Research
Classifier: Programming Language :: Python :: 3
Classifier: Topic :: Scientific/Engineering :: Artificial Intelligence
License-File: LICENSE
Requires-Dist: tabulate
Requires-Dist: numpy
Requires-Dist: tqdm
Requires-Dist: jaxtyping
Requires-Dist: onnx
Requires-Dist: onnxruntime
Requires-Dist: pandas
Requires-Dist: usearch>=2.6.0
Provides-Extra: dev
Requires-Dist: datasets; extra == "dev"
Requires-Dist: mypy; extra == "dev"
Requires-Dist: pytest; extra == "dev"
Requires-Dist: flake8; extra == "dev"
Requires-Dist: pytest-cov; extra == "dev"
Requires-Dist: twine; extra == "dev"
Requires-Dist: tabulate; extra == "dev"
Requires-Dist: black; extra == "dev"
Requires-Dist: isort; extra == "dev"
Requires-Dist: tf2onnx; extra == "dev"
Provides-Extra: tensorflow
Requires-Dist: tensorflow<2.16,>=2.11; extra == "tensorflow"
